chainsaddiction/Makefile
chainsaddiction/__init__.py
chainsaddiction/dataset.c
chainsaddiction/dataset.h
chainsaddiction/err.h
chainsaddiction/libma.c
chainsaddiction/libma.h
chainsaddiction/poishmm.cpython-311-darwin.so
chainsaddiction/py.typed
chainsaddiction/read.c
chainsaddiction/read.h
chainsaddiction/restrict.h
chainsaddiction/scalar.h
chainsaddiction/typing.py
chainsaddiction/utils.cpython-311-darwin.so
chainsaddiction/poishmm/Makefile
chainsaddiction/poishmm/__init__.pyi
chainsaddiction/poishmm/pois-em.c
chainsaddiction/poishmm/pois-em.h
chainsaddiction/poishmm/pois-fwbw.c
chainsaddiction/poishmm/pois-fwbw.h
chainsaddiction/poishmm/pois-hmm.c
chainsaddiction/poishmm/pois-hmm.h
chainsaddiction/poishmm/pois-params.c
chainsaddiction/poishmm/pois-params.h
chainsaddiction/poishmm/pois-probs.c
chainsaddiction/poishmm/pois-probs.h
chainsaddiction/poishmm/poishmm-module.c
chainsaddiction/poishmm/poishmm-module.h
chainsaddiction/poishmm/poishmm-object.h
chainsaddiction/poishmm/tests/Makefile
chainsaddiction/poishmm/tests/runtest.c
chainsaddiction/poishmm/tests/test-pois-em.c
chainsaddiction/poishmm/tests/test-pois-em.h
chainsaddiction/poishmm/tests/test-pois-hmm.c
chainsaddiction/poishmm/tests/test-pois-hmm.h
chainsaddiction/poishmm/tests/test-pois-params.c
chainsaddiction/poishmm/tests/test-pois-params.h
chainsaddiction/poishmm/tests/test-pois-probs.c
chainsaddiction/poishmm/tests/test-pois-probs.h
chainsaddiction/poishmm/tests/data/earthquakes.lprobs
chainsaddiction/poishmm/tests/data/params-3s
chainsaddiction/poishmm/tests/data/params-4s
chainsaddiction/poishmm/tests/data/ppr1
chainsaddiction/poishmm/tests/data/ppr2
chainsaddiction/poishmm/tests/data/ppr3
chainsaddiction/poishmm/tests/data/ppr4
chainsaddiction/poishmm/tests/data/ppr5
chainsaddiction/poishmm/tests/data/std3s.poisparams
chainsaddiction/tests/Makefile
chainsaddiction/tests/runtest.c
chainsaddiction/tests/test-dataset.c
chainsaddiction/tests/test-dataset.h
chainsaddiction/tests/test-read.c
chainsaddiction-0.2.4.dist-info/LICENSE
chainsaddiction-0.2.4.dist-info/METADATA
chainsaddiction-0.2.4.dist-info/WHEEL
chainsaddiction-0.2.4.dist-info/top_level.txt
chainsaddiction-0.2.4.dist-info/RECORD
