Metadata-Version: 2.1
Name: chainsaddiction
Version: 0.2.4
Summary: HMM with Poisson-distributed latent variables.
Author-email: Michael Blaß <mblass@posteo.net>
License: Copyright 2019 Michael Blaß michael.blass@uni-hamburg.de
Project-URL: Repository, https://github.com/teagum/chainsaddiction
Project-URL: Documentation, https://chainsaddiction.rtfd.org
Keywords: hmm,poisson,hidden-markov model
Classifier: License :: OSI Approved :: BSD License
Classifier: Programming Language :: Python :: 3
Classifier: Programming Language :: Python :: 3.7
Classifier: Programming Language :: Python :: 3.8
Classifier: Programming Language :: Python :: 3.9
Classifier: Programming Language :: Python :: 3 :: Only
Classifier: Programming Language :: Python :: Implementation :: CPython
Classifier: Topic :: Scientific/Engineering
Classifier: Intended Audience :: Science/Research
Classifier: Intended Audience :: Information Technology
License-File: LICENSE
Requires-Dist: numpy
